multiHIVE/__init__.py
multiHIVE/model/__init__.py
multiHIVE/model/_multiHIVE.py
multiHIVE/module/__init__.py
multiHIVE/module/_multiHIVEvae.py
multiHIVE/nn/__init__.py
multiHIVE/nn/_base_components.py
multiHIVE/train/__init__.py
multiHIVE/train/_adversarialtrainingplan.py
multihive-0.1.0.dist-info/METADATA
multihive-0.1.0.dist-info/WHEEL
multihive-0.1.0.dist-info/RECORD
