Metadata-Version: 2.4
Name: multiHIVE
Version: 0.1.0
Summary: multiHIVE, a hierarchical multimodal deep generative model for integrating multiomics data
Project-URL: Homepage, https://github.com/Zafar-Lab/multiHIVE
Author-email: Anirudh Nanduri* <nandurianirudh28@gmail.com>, Musale Krushna Pavan* <krushna@cse.iitk.ac.in>, Kushagra Pandey <pandeyk1@uci.edu>, Hamim Zafar <hamim@iitk.ac.in>
License: MIT
Classifier: License :: OSI Approved :: MIT License
Classifier: Operating System :: OS Independent
Classifier: Programming Language :: Python :: 3
Requires-Python: >=3.11
Requires-Dist: anndata>=0.11.3
Requires-Dist: mudata>=0.3.1
Requires-Dist: scanpy==1.11.0
Requires-Dist: scikit-learn>=1.5.2
Requires-Dist: scipy>=1.15.2
Requires-Dist: scvi-tools==1.3.0
Requires-Dist: torch==2.6.0
